{
    "access-key": "e456ad86-34c9-4f00-8771-f78b048c98ed",
    "settings": {
        "StuckFree": true,
        "LevelingSpeed": 10,
        "ResetDoorsOnMovement": true,
        "BTAcceleration": true,
        "FixRopes": true,
        "ReplaceElevNameInAlarmMsg": true,
        "DisableJump": false,
        "BTWeldSystem": true,
        "WeldPlayers": false,
        "ErrorReport": true,
        "MoveCabToFloor": true,
        "FixFloorDetect": true,
        "FixFloorDetectStopBtn": true,
        "PreventDoorOpening": true,
        "FixStopping": true,
        "MovementEngine": "Legacy"
    },
    "permissions": {
        "global": {
            "DisableMenu": false,
            "ManageElevators": false,
            "ManagePermissions": false,
            "ManageSettings": false,
            "Regeneration": false,
            "Teleportation": true,
            "RegenAll": false,
            "ManageGlobalPermissions": false
        },
        "3897179013": {
            "RegenAll": true,
            "Teleportation": true,
            "ManageElevators": true,
            "Regeneration": true,
            "ManagePermissions": true,
            "DisableMenu": false,
            "ManageGlobalPermissions": true,
            "ManageSettings": true
        },
        "6097018432": {
            "RegenAll": true,
            "Teleportation": true,
            "ManageElevators": true,
            "Regeneration": true,
            "ManagePermissions": true,
            "DisableMenu": false,
            "ManageGlobalPermissions": true,
            "ManageSettings": true
        }
    }
}