{
    "access-key": "1fe50594-c014-419b-9a96-522a705af3fd",
    "settings": {
        "StuckFree": true,
        "LevelingSpeed": 10,
        "ResetDoorsOnMovement": true,
        "BTAcceleration": true,
        "FixRopes": true,
        "ReplaceElevNameInAlarmMsg": true,
        "DisableJump": false,
        "BTWeldSystem": true,
        "WeldPlayers": false,
        "ErrorReport": true,
        "MoveCabToFloor": true,
        "FixFloorDetect": true,
        "FixFloorDetectStopBtn": true,
        "PreventDoorOpening": true,
        "FixStopping": true,
        "MovementEngine": "Prismatic"
    },
    "permissions": {
        "global": {
            "DisableMenu": false,
            "ManageElevators": false,
            "ManagePermissions": false,
            "ManageSettings": false,
            "Regeneration": false,
            "Teleportation": true,
            "RegenAll": false,
            "ManageGlobalPermissions": false
        }
    }
}